{
    "handler": "Microsoft.Compute.MultiVm",
    "version": "0.1.2-preview",
    "parameters": {
        "basics": [
            {
                "name": "vmUsername",
                "type": "Microsoft.Compute.UserNameTextBox",
                "label": "VM user name",
                "defaultValue": "",
                "toolTip": "",
                "constraints": {
                    "required": true
                },
                "osPlatform": "Linux"
            },
            {
                "name": "vmPassword",
                "type": "Microsoft.Common.PasswordBox",
                "label": {
                    "password": "VM user password",
                    "confirmPassword": "Confirm password"
                },
                "toolTip": "",
                "constraints": {
                    "required": true,
                    "regex": "^((?=.*[0-9])(?=.*[a-z])(?=.*[A-Z])|(?=.*[0-9])(?=.*[a-z])(?=.*[!@#$%^&*])|(?=.*[0-9])(?=.*[A-Z])(?=.*[!@#$%^&*])|(?=.*[a-z])(?=.*[A-Z])(?=.*[!@#$%^&*])).{12,72}$",
                    "validationMessage": "Password must be at least 12 characters long and have 3 out of the following: one number, one lower case, one upper case, or one special character"
                },
                "options": {
                    "hideConfirmation": false
                }
            }
        ],
        "steps": [
            {
                "name": "striimSettings",
                "label": "Striim Cluster Settings",
                "subLabel": {
                    "preValidation": "Configure Striim Cluster",
                    "postValidation": "Done"
                },
                "bladeTitle": "Striim Cluster Settings",
                "elements": [
                    {
                        "name": "deploymentType",
                        "type": "Microsoft.Common.DropDown",
                        "label": "Striim deployment type",
                        "defaultValue": "Standalone",
                        "toolTip": "Standalone mode deployment will deploy striim server on a single VM of size Standard_F4s. Cluster mode deployment will deploy striim servers on 2 or more VMs on selected VM size.", 
                        "constraints": {
                            "allowedValues": [
                                {
                                    "label": "Standalone",
                                    "value": "Standalone"
                                },
                                {
                                    "label": "Cluster",
                                    "value": "Cluster"
                                }
                            ]
                        }
                    },
                    {
                        "name": "clusterVmCount",
                        "type": "Microsoft.Common.DropDown",
                        "label": "Number of VMs in Striim cluster",
                        "defaultValue": "2",
                        "toolTip": "Number of VMs in the Striim cluster",
                        "constraints": {
                            "allowedValues": [
                                {
                                    "label": "2",
                                    "value": 2
                                },
                                {
                                    "label": "3",
                                    "value": 3
                                },
                                {
                                    "label": "4",
                                    "value": 4
                                },
                                {
                                    "label": "5",
                                    "value": 5
                                },
                                {
                                    "label": "6",
                                    "value": 6
                                },
                                {
                                    "label": "7",
                                    "value": 7
                                },
                                {
                                    "label": "8",
                                    "value": 8
                                }
                            ]
                        },
                        "visible": "[equals(steps('striimSettings').deploymentType, 'Cluster')]"
                    },
                    {
                        "name": "solutionSizeStandalone",
                        "type": "Microsoft.Compute.SizeSelector",
                        "label": "Striim Solution Size",
                        "toolTip": "Select the right size for your requirement. Basic=Standard_F4s, Regular=Standard_F8s, Enterprise=Standard_DS4_v2, Premium=Standard_DS5_v2",
                        "recommendedSizes": [
                            "Standard_F4s",
                            "Standard_F8s",
                            "Standard_DS4_v2",
                            "Standard_DS5_v2"
                        ],  
                        "constraints": {
                            "allowedSizes": [
                                "Standard_F4s",
                                "Standard_F8s",
                                "Standard_DS4_v2",
                                "Standard_DS5_v2"
                            ] 
                        }, 
                        "osPlatform": "Linux",
                        "imageReference": {
                            "offer": "integrationforsqlserveronazure",
                            "publisher": "striim",
                            "sku": "v372"
                        },
                        "count": "1",
                        "visible": "[equals(steps('striimSettings').deploymentType, 'Standalone')]"
                    },
                    {
                        "name": "solutionSize",
                        "type": "Microsoft.Compute.SizeSelector",
                        "label": "Striim Solution Size",
                        "toolTip": "Select the right size for your requirement. Basic=Standard_F4s, Regular=Standard_F8s, Enterprise=Standard_DS4_v2, Premium=Standard_DS5_v2",
                        "recommendedSizes": [
                            "Standard_F4s",
                            "Standard_F8s",
                            "Standard_DS4_v2",
                            "Standard_DS5_v2"
                        ],  
                        "constraints": {
                            "allowedSizes": [
                                "Standard_F4s",
                                "Standard_F8s",
                                "Standard_DS4_v2",
                                "Standard_DS5_v2"
                            ] 
                        }, 
                        "osPlatform": "Linux",
                        "imageReference": {
                            "offer": "integrationforsqlserveronazure",
                            "publisher": "striim",
                            "sku": "v372"
                        },
                        "count": "[steps('striimSettings').clusterVmCount]",
                        "visible": "[equals(steps('striimSettings').deploymentType, 'Cluster')]"
                    },
                    {
                        "name": "striimClusterName",
                        "type": "Microsoft.Common.TextBox",
                        "label": "Name of the Striim Cluster",
                        "defaultValue": "",
                        "toolTip": "Enter a unique logical name for the Striim cluster",
                        "constraints": {
                            "required": true,
                            "regex" : "^[a-z]{3,20}$",
                            "validationMessage": "Use a name between 3 and 20 character long with only lowercase alphabets"
                        }
                    },
                    {
                        "name": "striimClusterPassword",
                        "type": "Microsoft.Common.PasswordBox",
                        "label": {
                            "password": "Striim Cluster password",
                            "confirmPassword": "Confirm cluster password"
                        },
                        "toolTip": "",
                        "constraints": {
                            "required": true,
                            "regex": "^((?=.*[0-9])(?=.*[a-z])(?=.*[A-Z])|(?=.*[0-9])(?=.*[a-z])(?=.*[!@#$%^&*])|(?=.*[0-9])(?=.*[A-Z])(?=.*[!@#$%^&*])|(?=.*[a-z])(?=.*[A-Z])(?=.*[!@#$%^&*])).{12,72}$",
                            "validationMessage": "Password must be at least 12 characters long and have 3 out of the following: one number, one lower case, one upper case, or one special character"
                        },
                        "options": {
                            "hideConfirmation": false
                        }
                    }
                ]
            },
            {
                "name": "accessSettings",
                "label": "Striim Access Settings",
                "subLabel": {
                    "preValidation": "Configure how you access the Striim",
                    "postValidation": "Done"
                },
                "bladeTitle": "Striim Access Settings",
                "elements": [
                    {
                        "name": "striimDomainName",
                        "type": "Microsoft.Network.PublicIpAddressCombo",
                        "label": {
                            "publicIpAddress": "Public IP address",
                            "domainNameLabel": "Domain name for Striim"
                        },
                        "toolTip": {
                            "domainNameLabel": "Striim will be accessible from this domain"
                        },
                        "defaultValue": {
                            "publicIpAddressName": "striimMasterNodeIP",
                            "domainNameLabel": "change_me_to_be_unique"
                        },
                        "constraints": {
                            "required": {
                                "domainNameLabel": true
                            }
                        },
                        "options": {
                            "hideDomainNameLabel": false,
                            "hideNone": true,
                            "hideExisting": true
                        }
                    },
                    {
                        "name": "striimAdminPassword",
                        "type": "Microsoft.Common.PasswordBox",
                        "label": {
                            "password": "Striim admin password",
                            "confirmPassword": "Confirm admin password"
                        },
                        "toolTip": "",
                        "constraints": {
                            "required": true,
                            "regex": "^((?=.*[0-9])(?=.*[a-z])(?=.*[A-Z])|(?=.*[0-9])(?=.*[a-z])(?=.*[!@#$%^&*])|(?=.*[0-9])(?=.*[A-Z])(?=.*[!@#$%^&*])|(?=.*[a-z])(?=.*[A-Z])(?=.*[!@#$%^&*])).{12,72}$",
                            "validationMessage": "Password must be at least 12 characters long and have 3 out of the following: one number, one lower case, one upper case, or one special character"
                        },
                        "options": {
                            "hideConfirmation": false
                        }
                    }
                ]
            }
        ],
        "outputs": {
            "adminUserName": "[basics('vmUsername')]",
            "adminPassword": "[basics('vmPassword')]",
            "dnsPrefix": "[steps('accessSettings').striimDomainName.domainNameLabel]",
            "solutionSizeCluster": "[steps('striimSettings').solutionSize]",
            "solutionSizeStandalone": "[steps('striimSettings').solutionSizeStandalone]",
            "deploymentType": "[steps('striimSettings').deploymentType]",
            "clusterNodeCount": "[steps('striimSettings').clusterVmCount]",
            "clusterName": "[steps('striimSettings').striimClusterName]",
            "clusterPassword": "[steps('striimSettings').striimClusterPassword]",
            "striimAdminPassword": "[steps('accessSettings').striimAdminPassword]",
            "location": "[location()]"
        }
    }
}
